mtms/__init__.py
mtms/base/__init__.py
mtms/base/configs.py
mtms/base/classes/Admin.py
mtms/base/classes/CardOperation.py
mtms/base/classes/ConsoleTable.py
mtms/base/classes/Counter.py
mtms/base/classes/Payment.py
mtms/base/classes/TokenOperation.py
mtms/base/classes/__init__.py
mtms/base/functions/__init__.py
mtms/base/functions/functions.py
mtms/base/menu/__init__.py
mtms/base/menu/admin_menu.py
mtms/base/menu/counter_menu.py
mtms/base/menu/customer_menu.py
mtms/base/menu/main_menu.py
mtms/initials/__init__.py
mtms/initials/database/metro_db_struct.sql
mtms/initials/lang/en.json
mtms/lang/en.json
mtms/lang/hi.json
mtms-1.0.3.dist-info/LICENSE
mtms-1.0.3.dist-info/METADATA
mtms-1.0.3.dist-info/WHEEL
mtms-1.0.3.dist-info/top_level.txt
mtms-1.0.3.dist-info/RECORD
