Metadata-Version: 2.1
Name: mtms
Version: 1.0.3
Summary: Metro Train Management System
Home-page: https://github.com/govindgrover/mtms
Author: Govind Grover
Author-email: ask@govindgrover.com
License: UNKNOWN
Platform: UNKNOWN
Classifier: Programming Language :: Python :: 3
Classifier: License :: OSI Approved :: GNU General Public License v3 or later (GPLv3+)
Classifier: Operating System :: OS Independent
Classifier: Natural Language :: English
Classifier: Natural Language :: Hindi
Classifier: Topic :: Education
Requires-Python: >=3.6
License-File: LICENSE
Requires-Dist: mysql.connector
Requires-Dist: uuid
Requires-Dist: pyqrcode
